ants_worker/__init__.py
ants_worker/agent.py
ants_worker/api_client.py
ants_worker/cli.py
ants_worker/config.py
ants_worker/hardware.py
ants_worker/standalone.py
ants_worker/stigmergic.py
ants_worker/core/__init__.py
ants_worker/core/crypto.py
ants_worker/core/protocol.py
ants_worker/core/worker.py
ants_worker/plugins/__init__.py
ants_worker/plugins/registry.py
ants_worker/plugins/cloud/__init__.py
ants_worker/plugins/cloud/lambda_.py
ants_worker/plugins/cloud/local.py
ants_worker/plugins/cloud/vastai.py
ants_worker/plugins/compute/__init__.py
ants_worker/plugins/compute/amd_npu.py
ants_worker/plugins/compute/amd_rocm.py
ants_worker/plugins/compute/cpu.py
ants_worker/plugins/compute/cuda.py
ants_worker/plugins/compute/kangaroo_bin.py
ants_worker-0.2.4.dist-info/METADATA
ants_worker-0.2.4.dist-info/WHEEL
ants_worker-0.2.4.dist-info/entry_points.txt
ants_worker-0.2.4.dist-info/top_level.txt
ants_worker-0.2.4.dist-info/RECORD
