Metadata-Version: 2.4
Name: ants-worker
Version: 0.2.4
Summary: Distributed compute worker for Ants at Work colony
Author-email: Ants at Work <hello@ants-at-work.com>
Project-URL: Homepage, https://ants-at-work.com
Project-URL: Documentation, https://github.com/ants-at-work/worker
Project-URL: Repository, https://github.com/ants-at-work/worker
Project-URL: Issues, https://github.com/ants-at-work/worker/issues
Keywords: distributed,compute,gpu,npu,amd,ryzen-ai,kangaroo,ecdlp
Classifier: Development Status :: 4 - Beta
Classifier: Environment :: Console
Classifier: Intended Audience :: Developers
Classifier: Operating System :: OS Independent
Classifier: Programming Language :: Python :: 3
Classifier: Programming Language :: Python :: 3.10
Classifier: Programming Language :: Python :: 3.11
Classifier: Programming Language :: Python :: 3.12
Classifier: Topic :: Scientific/Engineering :: Mathematics
Requires-Python: >=3.10
Requires-Dist: click>=8.0
Requires-Dist: rich>=13.0
Requires-Dist: httpx>=0.25.0
Provides-Extra: cuda
Requires-Dist: cupy-cuda12x>=12.0; extra == "cuda"
Provides-Extra: amd
Requires-Dist: torch>=2.0; extra == "amd"
Requires-Dist: pyopencl>=2023.1; extra == "amd"
Provides-Extra: npu
Requires-Dist: onnxruntime-directml>=1.16.0; extra == "npu"
Provides-Extra: gpu
Requires-Dist: cupy-cuda12x>=12.0; extra == "gpu"
Provides-Extra: agent
Requires-Dist: uagents>=0.6.0; extra == "agent"
Provides-Extra: typedb
Requires-Dist: typedb-driver>=3.0.0; extra == "typedb"
Provides-Extra: dev
Requires-Dist: pytest>=7.0; extra == "dev"
Requires-Dist: pytest-asyncio>=0.21; extra == "dev"
Requires-Dist: black>=23.0; extra == "dev"
Requires-Dist: mypy>=1.0; extra == "dev"
Provides-Extra: all
Requires-Dist: ants-worker[agent,amd,cuda,dev,typedb]; extra == "all"
